factorial_nam/__init__.py
factorial_nam-0.1.0.dist-info/METADATA
factorial_nam-0.1.0.dist-info/WHEEL
factorial_nam-0.1.0.dist-info/RECORD
